opytz/__init__.py
opytz/exceptions.py
opytz/lazy.py
opytz/reference.py
opytz/tzfile.py
opytz/tzinfo.py
opytz/zoneinfo/CET
opytz/zoneinfo/CST6CDT
opytz/zoneinfo/Cuba
opytz/zoneinfo/EET
opytz/zoneinfo/EST
opytz/zoneinfo/EST5EDT
opytz/zoneinfo/Egypt
opytz/zoneinfo/Eire
opytz/zoneinfo/Factory
opytz/zoneinfo/GB
opytz/zoneinfo/GB-Eire
opytz/zoneinfo/GMT
opytz/zoneinfo/GMT+0
opytz/zoneinfo/GMT-0
opytz/zoneinfo/GMT0
opytz/zoneinfo/Greenwich
opytz/zoneinfo/HST
opytz/zoneinfo/Hongkong
opytz/zoneinfo/Iceland
opytz/zoneinfo/Iran
opytz/zoneinfo/Israel
opytz/zoneinfo/Jamaica
opytz/zoneinfo/Japan
opytz/zoneinfo/Kwajalein
opytz/zoneinfo/Libya
opytz/zoneinfo/MET
opytz/zoneinfo/MST
opytz/zoneinfo/MST7MDT
opytz/zoneinfo/NZ
opytz/zoneinfo/NZ-CHAT
opytz/zoneinfo/Navajo
opytz/zoneinfo/PRC
opytz/zoneinfo/PST8PDT
opytz/zoneinfo/Poland
opytz/zoneinfo/Portugal
opytz/zoneinfo/ROC
opytz/zoneinfo/ROK
opytz/zoneinfo/Singapore
opytz/zoneinfo/Turkey
opytz/zoneinfo/UCT
opytz/zoneinfo/UTC
opytz/zoneinfo/Universal
opytz/zoneinfo/W-SU
opytz/zoneinfo/WET
opytz/zoneinfo/Zulu
opytz/zoneinfo/iso3166.tab
opytz/zoneinfo/localtime
opytz/zoneinfo/posixrules
opytz/zoneinfo/zone.tab
opytz/zoneinfo/zone1970.tab
opytz/zoneinfo/Africa/Abidjan
opytz/zoneinfo/Africa/Accra
opytz/zoneinfo/Africa/Addis_Ababa
opytz/zoneinfo/Africa/Algiers
opytz/zoneinfo/Africa/Asmara
opytz/zoneinfo/Africa/Asmera
opytz/zoneinfo/Africa/Bamako
opytz/zoneinfo/Africa/Bangui
opytz/zoneinfo/Africa/Banjul
opytz/zoneinfo/Africa/Bissau
opytz/zoneinfo/Africa/Blantyre
opytz/zoneinfo/Africa/Brazzaville
opytz/zoneinfo/Africa/Bujumbura
opytz/zoneinfo/Africa/Cairo
opytz/zoneinfo/Africa/Casablanca
opytz/zoneinfo/Africa/Ceuta
opytz/zoneinfo/Africa/Conakry
opytz/zoneinfo/Africa/Dakar
opytz/zoneinfo/Africa/Dar_es_Salaam
opytz/zoneinfo/Africa/Djibouti
opytz/zoneinfo/Africa/Douala
opytz/zoneinfo/Africa/El_Aaiun
opytz/zoneinfo/Africa/Freetown
opytz/zoneinfo/Africa/Gaborone
opytz/zoneinfo/Africa/Harare
opytz/zoneinfo/Africa/Johannesburg
opytz-2016.18.dist-info/LICENSE.txt
opytz-2016.18.dist-info/METADATA
opytz-2016.18.dist-info/WHEEL
opytz-2016.18.dist-info/top_level.txt
opytz-2016.18.dist-info/zip-safe
opytz-2016.18.dist-info/RECORD
