Metadata-Version: 2.1
Name: opytz
Version: 2016.18
Summary: World timezone definitions, modern and historical
Home-page: http://pythonhosted.org/pytz
Author: Stuart Bishop
Author-email: stuart@stuartbishop.net
Maintainer: Stuart Bishop
Maintainer-email: stuart@stuartbishop.net
License: MIT
Download-URL: http://pypi.python.org/pypi/pytz
Keywords: timezone,tzinfo,datetime,olson,time
Platform: Independant
Classifier: Development Status :: 6 - Mature
Classifier: Intended Audience :: Developers
Classifier: License :: OSI Approved :: MIT License
Classifier: Natural Language :: English
Classifier: Operating System :: OS Independent
Classifier: Programming Language :: Python
Classifier: Programming Language :: Python :: 3
Classifier: Topic :: Software Development :: Libraries :: Python Modules
License-File: LICENSE.txt
